elm_fluent/__init__.py
elm_fluent/cli.py
elm_fluent/codegen.py
elm_fluent/compiler.py
elm_fluent/elm_fluent.py
elm_fluent/error_types.py
elm_fluent/html_compiler.py
elm_fluent/inference.py
elm_fluent/run.py
elm_fluent/types.py
elm_fluent/utils.py
elm_fluent/stubs/__init__.py
elm_fluent/stubs/date.py
elm_fluent/stubs/defaults.py
elm_fluent/stubs/fluent.py
elm_fluent/stubs/html.py
elm_fluent/stubs/html_attributes.py
elm_fluent/stubs/intl_datetimeformat.py
elm_fluent/stubs/intl_locale.py
elm_fluent/stubs/intl_numberformat.py
elm_fluent/stubs/intl_pluralrules.py
elm_fluent/stubs/intl_timezone.py
elm_fluent/stubs/string.py
elm_fluent-0.7.0.dist-info/licenses/AUTHORS.rst
elm_fluent-0.7.0.dist-info/licenses/LICENSE
elm_fluent-0.7.0.dist-info/METADATA
elm_fluent-0.7.0.dist-info/WHEEL
elm_fluent-0.7.0.dist-info/entry_points.txt
elm_fluent-0.7.0.dist-info/top_level.txt
elm_fluent-0.7.0.dist-info/RECORD
