Metadata-Version: 2.4
Name: elm-fluent
Version: 0.7.0
Summary: Fluent i18n solution for Elm
Author-email: Luke Plant <luke@lukeplant.me.uk>
License: MIT
Project-URL: HomePage, https://github.com/elm-fluent/elm-fluent
Keywords: fluent,localization,l10n,projectfluent,ftl,elm
Classifier: Development Status :: 4 - Beta
Classifier: Intended Audience :: Developers
Classifier: License :: OSI Approved :: MIT License
Classifier: Natural Language :: English
Classifier: Programming Language :: Python :: 3
Classifier: Programming Language :: Python :: 3.10
Classifier: Programming Language :: Python :: 3.11
Classifier: Programming Language :: Python :: 3.12
Classifier: Programming Language :: Python :: 3.13
Classifier: Programming Language :: Python :: 3.14
Requires-Python: >=3.10
License-File: LICENSE
License-File: AUTHORS.rst
Requires-Dist: beautifulsoup4>=4.6.3
Requires-Dist: click>=6.0
Requires-Dist: fluent-syntax>=0.15
Requires-Dist: fs>=2.4.2
Requires-Dist: language-tags>=0.4.4
Requires-Dist: lxml>=4.2.4
Requires-Dist: watchdog>=0.8.3
Dynamic: license-file
